tl3api/__init__.py
tl3api/base.py
tl3api/comment.py
tl3api/high_score.py
tl3api/map.py
tl3api/user.py
tl3api/wrapper.py
tl3api-1.2.0.dist-info/LICENSE
tl3api-1.2.0.dist-info/METADATA
tl3api-1.2.0.dist-info/WHEEL
tl3api-1.2.0.dist-info/top_level.txt
tl3api-1.2.0.dist-info/RECORD
