Metadata-Version: 2.1
Name: tl3api
Version: 1.2.0
Summary: An asynchronous API wrapper for the Traffic Lanes 3 / Intersection Controller API.
Home-page: https://github.com/Feeeeddmmmeee/tl3api
Author: Feeeeddmmmeee
License: MIT
Keywords: api,ic,tl3,wrapper,async
Platform: UNKNOWN
Classifier: Development Status :: 5 - Production/Stable
Classifier: Intended Audience :: Developers
Classifier: Operating System :: Microsoft :: Windows :: Windows 10
Classifier: License :: OSI Approved :: MIT License
Classifier: Programming Language :: Python :: 3
Requires: aiohttp
License-File: LICENSE
